azure/mgmt/workloadorchestration/__init__.py
azure/mgmt/workloadorchestration/_client.py
azure/mgmt/workloadorchestration/_configuration.py
azure/mgmt/workloadorchestration/_patch.py
azure/mgmt/workloadorchestration/_version.py
azure/mgmt/workloadorchestration/py.typed
azure/mgmt/workloadorchestration/_utils/__init__.py
azure/mgmt/workloadorchestration/_utils/model_base.py
azure/mgmt/workloadorchestration/_utils/serialization.py
azure/mgmt/workloadorchestration/aio/__init__.py
azure/mgmt/workloadorchestration/aio/_client.py
azure/mgmt/workloadorchestration/aio/_configuration.py
azure/mgmt/workloadorchestration/aio/_patch.py
azure/mgmt/workloadorchestration/aio/operations/__init__.py
azure/mgmt/workloadorchestration/aio/operations/_operations.py
azure/mgmt/workloadorchestration/aio/operations/_patch.py
azure/mgmt/workloadorchestration/models/__init__.py
azure/mgmt/workloadorchestration/models/_enums.py
azure/mgmt/workloadorchestration/models/_models.py
azure/mgmt/workloadorchestration/models/_patch.py
azure/mgmt/workloadorchestration/operations/__init__.py
azure/mgmt/workloadorchestration/operations/_operations.py
azure/mgmt/workloadorchestration/operations/_patch.py
azure_mgmt_workloadorchestration-1.0.0b1.dist-info/licenses/LICENSE
azure_mgmt_workloadorchestration-1.0.0b1.dist-info/METADATA
azure_mgmt_workloadorchestration-1.0.0b1.dist-info/WHEEL
azure_mgmt_workloadorchestration-1.0.0b1.dist-info/top_level.txt
azure_mgmt_workloadorchestration-1.0.0b1.dist-info/RECORD
